lls_core/__init__.py
lls_core/config.py
lls_core/cropping.py
lls_core/deconvolution.py
lls_core/llsz_core.py
lls_core/types.py
lls_core/utils.py
lls_core/workflow.py
lls_core/writers.py
lls_core/cmds/__init__.py
lls_core/cmds/__main__.py
lls_core/models/__init__.py
lls_core/models/crop.py
lls_core/models/deconvolution.py
lls_core/models/deskew.py
lls_core/models/lattice_data.py
lls_core/models/output.py
lls_core/models/results.py
lls_core/models/utils.py
lls_core/sample/__init__.py
lls_core-1.0.6.dist-info/METADATA
lls_core-1.0.6.dist-info/WHEEL
lls_core-1.0.6.dist-info/entry_points.txt
lls_core-1.0.6.dist-info/top_level.txt
lls_core-1.0.6.dist-info/RECORD
