Metadata-Version: 2.4
Name: lls_core
Version: 1.0.6
Summary: Core functionality for analysing and visualizing lattice lightsheet and Oblique Plane Microscopy data.
Author: Pradeep Rajasekhar, Lachlan Whitehead, Robert Haase, Michael Milton
License: GPL-3.0-only
Project-URL: Repository, https://github.com/BioimageAnalysisCoreWEHI/napari_lattice
Project-URL: BugTracker, https://github.com/BioimageAnalysisCoreWEHI/napari_lattice/issues
Project-URL: Documentation, https://bioimageanalysiscorewehi.github.io/napari_lattice/
Project-URL: SourceCode, https://github.com/BioimageAnalysisCoreWEHI/napari_lattice
Project-URL: UserSupport, https://github.com/BioimageAnalysisCoreWEHI/napari_lattice/issues
Classifier: Development Status :: 2 - Pre-Alpha
Classifier: Intended Audience :: Developers
Classifier: Framework :: napari
Classifier: Topic :: Software Development :: Testing
Classifier: Programming Language :: Python
Classifier: Programming Language :: Python :: 3
Classifier: Programming Language :: Python :: 3.8
Classifier: Programming Language :: Python :: 3.9
Classifier: Programming Language :: Python :: 3.10
Classifier: Operating System :: OS Independent
Classifier: License :: OSI Approved :: GNU General Public License v3 (GPLv3)
Requires-Python: >=3.8
Requires-Dist: aicsimageio>=4.6.3
Requires-Dist: aicspylibczi>=3.1.1
Requires-Dist: click
Requires-Dist: dask
Requires-Dist: dask[distributed]
Requires-Dist: fsspec>=2022.8.2
Requires-Dist: importlib_resources
Requires-Dist: napari-workflows>=0.2.8
Requires-Dist: npy2bdv
Requires-Dist: numpy<2
Requires-Dist: pandas
Requires-Dist: pyclesperanto_prototype>=0.20.0
Requires-Dist: pyopencl
Requires-Dist: pydantic<3,>=1.10.17
Requires-Dist: pyyaml
Requires-Dist: ome-types<0.6.0
Requires-Dist: read-roi
Requires-Dist: rich
Requires-Dist: resource-backed-dask-array>=0.1.0
Requires-Dist: scikit-image
Requires-Dist: StrEnum
Requires-Dist: tifffile<2025.2.18,>=2023.3.15
Requires-Dist: toolz
Requires-Dist: tqdm
Requires-Dist: typer<0.17.0
Requires-Dist: typing_extensions>=4.7.0
Requires-Dist: xarray[parallel]
Requires-Dist: zarr<3,>=2.16
Requires-Dist: numcodecs>=0.11
Provides-Extra: testing
Requires-Dist: tox; extra == "testing"
Requires-Dist: pytest; extra == "testing"
Requires-Dist: pytest-cov; extra == "testing"
Requires-Dist: napari; extra == "testing"
Provides-Extra: deconvolution
Requires-Dist: pycudadecon~=0.5; extra == "deconvolution"
Requires-Dist: numpy<2; extra == "deconvolution"
Provides-Extra: docs
Requires-Dist: mkdocstrings[python]; extra == "docs"
Requires-Dist: mkdocs-click; extra == "docs"
Requires-Dist: mkdocs-material; extra == "docs"
Requires-Dist: mkdocs-video; extra == "docs"
Requires-Dist: mkdocs-jupyter; extra == "docs"
Requires-Dist: fieldz>=0.1.0; extra == "docs"
Requires-Dist: griffe-fieldz; extra == "docs"
Provides-Extra: deploy
Requires-Dist: build; extra == "deploy"
Requires-Dist: twine; extra == "deploy"
